doblib/__init__.py
doblib/__main__.py
doblib/action.py
doblib/aggregate.py
doblib/base.py
doblib/ci.py
doblib/env.py
doblib/freeze.py
doblib/migrate.py
doblib/module.py
doblib/run.py
doblib/utils.py
doblib-0.20.6.dist-info/METADATA
doblib-0.20.6.dist-info/WHEEL
doblib-0.20.6.dist-info/entry_points.txt
doblib-0.20.6.dist-info/top_level.txt
doblib-0.20.6.dist-info/RECORD
