Metadata-Version: 2.4
Name: doblib
Version: 0.20.6
Summary: Management tool for Odoo installations
Home-page: https://github.com/initos/dob-lib
Author: initOS GmbH
Author-email: info@initos.com
Keywords: odoo environment management
Classifier: Environment :: Console
Classifier: License :: OSI Approved :: Apache Software License
Classifier: Operating System :: OS Independent
Classifier: Programming Language :: Python :: 3
Requires-Python: >=3.6
Requires-Dist: coverage
Requires-Dist: git-aggregator
Requires-Dist: ipython
Requires-Dist: pylint_odoo
Requires-Dist: python-dateutil
Requires-Dist: pytest-cov
Requires-Dist: pytest-odoo
Requires-Dist: PyYAML
Provides-Extra: no-ruff
Requires-Dist: black; extra == "no-ruff"
Requires-Dist: flake8; extra == "no-ruff"
Requires-Dist: isort>=4.3.10; extra == "no-ruff"
Provides-Extra: ruff
Requires-Dist: ruff; extra == "ruff"
